plover_local_env_var/__init__.py
plover_local_env_var/extension.py
plover_local_env_var/config/__init__.py
plover_local_env_var/config/file.py
plover_local_env_var/config/loader.py
plover_local_env_var/config/transformer.py
plover_local_env_var/env_var/__init__.py
plover_local_env_var/env_var/command.py
plover_local_env_var/env_var/expander.py
plover_local_env_var-0.3.9.dist-info/LICENSE.txt
plover_local_env_var-0.3.9.dist-info/METADATA
plover_local_env_var-0.3.9.dist-info/WHEEL
plover_local_env_var-0.3.9.dist-info/entry_points.txt
plover_local_env_var-0.3.9.dist-info/top_level.txt
plover_local_env_var-0.3.9.dist-info/zip-safe
plover_local_env_var-0.3.9.dist-info/RECORD
